{
    "start": "Début",
    "continue": "Continuer",
    "save": "Sauver",
    "load": "Charge",
    "erase": "Effacer",
    "back": "Arrière",
    "quit": "Quitter",
    "extra": "Supplémentaire",
    "settings": "Paramètres",
    "controls": "Contrôles",
    "language": "Langue",
    "audio": "L'audio",
    "volume": "Le volume",
    "sound": "Du son",
    "music": "Musique",
    "mute": "Muet",
    "graphics": "Graphique",
    "quality": "Qualité",
    "high": "Haut",
    "medium": "Moyen",
    "low": "Faible",
    "windowed": "Fenêtré",
    "full_screen": "Plein écran",
    "date": "Date",
    "time": "Temps",
    "second": "Seconde",
    "minute": "Minute",
    "hour": "Heure",
    "day": "Jour",
    "month": "Mois",
    "year": "An",
    "decade": "Décennie",
    "century": "Siècle",
    "monday": "Lundi",
    "tuesday": "Mardi",
    "wednesday": "Mercredi",
    "thursday": "Jeudi",
    "friday": "Vendredi",
    "saturday": "Samedi",
    "sunday": "Dimanche",
    "january": "Janvier",
    "february": "Février",
    "march": "Mars",
    "april": "Avril",
    "may": "Mai",
    "june": "Juin",
    "july": "Juillet",
    "august": "Août",
    "september": "Septembre",
    "october": "Octobre",
    "november": "Novembre",
    "december": "Décembre"
}